scraperweapon/__init__.py
scraperweapon/browser_emulator.py
scraperweapon/captcha_solver.py
scraperweapon/proxy_manager.py
scraperweapon/scraper.py
scraperweapon/utils.py
scraperweapon-1.0.0.dist-info/LICENSE
scraperweapon-1.0.0.dist-info/METADATA
scraperweapon-1.0.0.dist-info/WHEEL
scraperweapon-1.0.0.dist-info/top_level.txt
scraperweapon-1.0.0.dist-info/RECORD
