Metadata-Version: 2.1
Name: scraperweapon
Version: 1.0.0
Summary: A revolutionary web scraping library
Home-page: https://github.com/Sumedh1599/scraperweapon
Author: SumedhP
Author-email: your.email@example.com
License: UNKNOWN
Platform: UNKNOWN
Classifier: Programming Language :: Python :: 3
Classifier: License :: OSI Approved :: MIT License
Classifier: Operating System :: OS Independent
Requires-Python: >=3.7
License-File: LICENSE
Requires-Dist: requests
Requires-Dist: beautifulsoup4
Requires-Dist: playwright
